critswhitelist/__init__.py
critswhitelist/critswhitelist.py
critswhitelist-0.2.0.dist-info/METADATA
critswhitelist-0.2.0.dist-info/RECORD
critswhitelist-0.2.0.dist-info/WHEEL
critswhitelist-0.2.0.dist-info/top_level.txt
