Metadata-Version: 2.1
Name: critswhitelist
Version: 0.2.0
Summary: Library that interacts with CRITS to build an indicator whitelist system.
Home-page: https://github.com/automationator/critswhitelist
Author: Matthew Wilson
Author-email: automationator@runbox.com
License: Apache 2.0
Keywords: critswhitelist
Platform: UNKNOWN
Classifier: Development Status :: 3 - Alpha
Classifier: Intended Audience :: Developers
Classifier: Topic :: Software Development :: Build Tools
Classifier: License :: OSI Approved :: Apache Software License
Classifier: Programming Language :: Python :: 3
Classifier: Programming Language :: Python :: 3.3
Classifier: Programming Language :: Python :: 3.4
Classifier: Programming Language :: Python :: 3.5
Requires-Dist: urlfinderlib
